{
  "sections": {
    "main": {
      "type": "cancel-form",
      "blocks": {
        "790b91c7-db95-4ee7-a719-f1d4e69abc12": {
          "type": "text",
          "settings": {
          }
        },
        "37e845f9-4bd3-420d-9a91-e4b7a38a0018": {
          "type": "form",
          "settings": {
          }
        },
        "30ba823e-d4ab-4c9e-a028-3db387445930": {
          "type": "textarea",
          "settings": {
            "footer_text": "לתשומת ליבך, בהיעדר פרטים שיאפשרו לזהות את העסקה ו\/או את המוצר\/ים מתוך העסקה שהנך מבקש\/ת לבטל, יחול עיכוב בביטול עד להבהרת הפרטים באמצעות פרטי הקשר שבידי החברה. לידיעתך: במקרה בו המוצר כבר נשלח אלייך ממחסני החברה, הביטול יבוצע לאחר החזרתו למשרדי החברה או לאחת מחנויות הרשת באריזה המקורית וללא שנעשה בו שימוש."
          }
        }
      },
      "block_order": [
        "790b91c7-db95-4ee7-a719-f1d4e69abc12",
        "37e845f9-4bd3-420d-9a91-e4b7a38a0018",
        "30ba823e-d4ab-4c9e-a028-3db387445930"
      ],
      "settings": {
      }
    }
  },
  "order": [
    "main"
  ]
}